README.md
setup.py
lbrlabs_pulumi_remotecertificate/__init__.py
lbrlabs_pulumi_remotecertificate/_utilities.py
lbrlabs_pulumi_remotecertificate/cert_thumb_print.py
lbrlabs_pulumi_remotecertificate/provider.py
lbrlabs_pulumi_remotecertificate/pulumi-plugin.json
lbrlabs_pulumi_remotecertificate/py.typed
lbrlabs_pulumi_remotecertificate.egg-info/PKG-INFO
lbrlabs_pulumi_remotecertificate.egg-info/SOURCES.txt
lbrlabs_pulumi_remotecertificate.egg-info/dependency_links.txt
lbrlabs_pulumi_remotecertificate.egg-info/not-zip-safe
lbrlabs_pulumi_remotecertificate.egg-info/requires.txt
lbrlabs_pulumi_remotecertificate.egg-info/top_level.txt